pr_comment_cli/__init__.py
pr_comment_cli/main.py
pr_comment_cli-0.1.0.dist-info/licenses/LICENSE
pr_comment_cli-0.1.0.dist-info/METADATA
pr_comment_cli-0.1.0.dist-info/WHEEL
pr_comment_cli-0.1.0.dist-info/entry_points.txt
pr_comment_cli-0.1.0.dist-info/top_level.txt
pr_comment_cli-0.1.0.dist-info/RECORD
